bjf/__init__.py
bjf/__main__.py
bjf-0.0.3.dist-info/LICENSE
bjf-0.0.3.dist-info/METADATA
bjf-0.0.3.dist-info/WHEEL
bjf-0.0.3.dist-info/top_level.txt
bjf-0.0.3.dist-info/RECORD
