Metadata-Version: 2.1
Name: bjf
Version: 0.0.3
Summary: Simple in-place JSON Formatter
Home-page: https://github.com/rohanwinsor/bjf
Author: rohan winsor
Author-email: rohan.w.charles@gmail.com
License: MIT
Platform: UNKNOWN
License-File: LICENSE
Requires-Dist: click (==8.1.0)
